mecs/Stem.py
mecs/__init__.py
mecs/lemma.py
mecs/mecs.py
mecs-1.0.3.dist-info/METADATA
mecs-1.0.3.dist-info/WHEEL
mecs-1.0.3.dist-info/top_level.txt
mecs-1.0.3.dist-info/RECORD
