Metadata-Version: 2.1
Name: mecs
Version: 1.0.3
Summary: Library for stemming Madurese text
